pyfred24/__init__.py
pyfred24/branch.py
pyfred24/client.py
pyfred24/fred_helper.py
pyfred24/leaf.py
pyfred24-0.1.dist-info/METADATA
pyfred24-0.1.dist-info/WHEEL
pyfred24-0.1.dist-info/top_level.txt
pyfred24-0.1.dist-info/RECORD
