Metadata-Version: 2.1
Name: pyfred24
Version: 0.1
Summary: Python wrapper for the US Federal Reserve FRED API
Home-page: https://github.com/tnemechek/pyfred
Author: Thomas Nemechek
Classifier: Programming Language :: Python :: 3
Classifier: License :: OSI Approved :: MIT License
Classifier: Operating System :: OS Independent
Requires-Python: >=3.6
Requires-Dist: requests
Requires-Dist: pandaspython-dotenv
